geolode/SampleMaker.py
geolode/ShapefileProcess.py
geolode/TifProcess.py
geolode/TifShpFilte.py
geolode/_init_.py
GeoLode-1.0.1.3.dist-info/LICENSE.txt
GeoLode-1.0.1.3.dist-info/METADATA
GeoLode-1.0.1.3.dist-info/WHEEL
GeoLode-1.0.1.3.dist-info/top_level.txt
GeoLode-1.0.1.3.dist-info/RECORD
