Metadata-Version: 2.1
Name: GeoLode
Version: 1.0.1.3
Summary: Python package designed for efficient geospatial data analysis
Home-page: 
Author: Anchenry
Author-email: anchenry.h@gmail.com
License: MIT
License-File: LICENSE.txt
